console_functions/__init__.py
console_functions/functions.py
console_functions-0.0.8.dist-info/LICENSE
console_functions-0.0.8.dist-info/METADATA
console_functions-0.0.8.dist-info/WHEEL
console_functions-0.0.8.dist-info/top_level.txt
console_functions-0.0.8.dist-info/RECORD
