Metadata-Version: 2.1
Name: console-functions
Version: 0.0.8
Summary: Some functions for easily printing pretty text to a terminal shell in python.
Home-page: https://github.com/christianblandford/Python-Shell-Functions
Author: Christian Blandford
Author-email: christianblandford@me.com
License: UNKNOWN
Platform: UNKNOWN
Classifier: Programming Language :: Python :: 3
Classifier: License :: OSI Approved :: MIT License
Classifier: Operating System :: OS Independent
Requires-Dist: termcolor (>=1.1.0)
Requires-Dist: pick (>=0.6.4)
